nonefield/__init__.py
nonefield/fields.py
nonefield/models.py
nonefield/widgets.py
nonefield/contrib/__init__.py
nonefield/contrib/drf_integration/__init__.py
nonefield/contrib/drf_integration/fields.py
nonefield/tests/__init__.py
nonefield/tests/base.py
nonefield/tests/constants.py
nonefield/tests/test_drf_integration.py
nonefield/tests/test_nonefield.py
django_nonefield-0.4.dist-info/LICENSE_GPL2.0.txt
django_nonefield-0.4.dist-info/LICENSE_LGPL_2.1.txt
django_nonefield-0.4.dist-info/METADATA
django_nonefield-0.4.dist-info/WHEEL
django_nonefield-0.4.dist-info/top_level.txt
django_nonefield-0.4.dist-info/RECORD
