Metadata-Version: 1.2
Name: django-nonefield
Version: 0.4
Summary: A None field for Django.
Home-page: https://github.com/barseghyanartur/django-nonefield/
Author: Artur Barseghyan
Author-email: artur.barseghyan@gmail.com
License: GPL-2.0-only OR LGPL-2.1-or-later
Project-URL: Bug Tracker, https://github.com/barseghyanartur/django-nonefield/
Project-URL: Documentation, https://django-nonefield.readthedocs.io/
Project-URL: Source Code, https://github.com/barseghyanartur/django-nonefield/
Project-URL: Changelog, https://django-nonefield.readthedocs.io/en/latest/changelog.html
Keywords: forms,django,none field,django rest framework
Platform: UNKNOWN
Classifier: Programming Language :: Python :: 2.7
Classifier: Programming Language :: Python :: 3
Classifier: Programming Language :: Python :: 3.6
Classifier: Programming Language :: Python :: 3.7
Classifier: Programming Language :: Python :: 3.8
Classifier: Environment :: Web Environment
Classifier: License :: OSI Approved :: GNU General Public License v2 (GPLv2)
Classifier: License :: OSI Approved :: GNU Lesser General Public License v2 or later (LGPLv2+)
Classifier: Framework :: Django
Classifier: Intended Audience :: Developers
Classifier: Operating System :: OS Independent
Classifier: Development Status :: 4 - Beta
